py_calc/__init__.py
py_calc/_version.py
py_calc/calc.py
py_calc/cli.py
py_calc-0.1.0.dist-info/AUTHORS.rst
py_calc-0.1.0.dist-info/LICENSE
py_calc-0.1.0.dist-info/METADATA
py_calc-0.1.0.dist-info/WHEEL
py_calc-0.1.0.dist-info/entry_points.txt
py_calc-0.1.0.dist-info/top_level.txt
py_calc-0.1.0.dist-info/RECORD
